mi_amore/__init__.py
mi_amore/_espresso.pyi
mi_amore/_espresso.so
mi_amore/cli.py
mi_amore/lib.c
mi_amore/minimize.py
mi_amore-0.1.3.dist-info/METADATA
mi_amore-0.1.3.dist-info/WHEEL
mi_amore-0.1.3.dist-info/entry_points.txt
mi_amore-0.1.3.dist-info/RECORD
mi_amore-0.1.3.dist-info/licenses/LICENSE
