Metadata-Version: 2.4
Name: mi-amore
Version: 0.1.3
Summary: Make Espresso love again
Author-Email: swayand <stefan.wayand@gmail.com>
License-Expression: GPL-3.0-or-later
License-File: LICENSE
Classifier: Programming Language :: Python :: 3
Classifier: Operating System :: MacOS
Classifier: Operating System :: POSIX :: Linux
Project-URL: Homepage, https://gitlab.com/gwhe/mi-amore
Project-URL: Repository, https://gitlab.com/gwhe/mi-amore
Project-URL: Issues, https://gitlab.com/gwhe/mi-amore/-/issues
Requires-Python: >=3.13
Requires-Dist: sympy>=1.14.0
Requires-Dist: typer>=0.15.2
